pep440deb.py
pep440deb-1.3.dist-info/METADATA
pep440deb-1.3.dist-info/RECORD
pep440deb-1.3.dist-info/WHEEL
pep440deb-1.3.dist-info/entry_points.txt
pep440deb-1.3.dist-info/top_level.txt
