Metadata-Version: 2.1
Name: pep440deb
Version: 1.3
Summary: Translate PEP440 version to Debian policy
Home-page: https://gitlab.com/bersace/pep440deb
Author: Étienne BERSAC
Author-email: bersace03@gmail.com
License: GPL-3.0+
Keywords: debian,dpkg,pep440,version
Platform: UNKNOWN
Requires-Dist: packaging
